lib_python_template-1.0.5.dist-info/METADATA
lib_python_template-1.0.5.dist-info/WHEEL
lib_python_template-1.0.5.dist-info/entry_points.txt
lib_python_template-1.0.5.dist-info/licenses/LICENSE
lib_python_template/__init__.py
lib_python_template/app.py
lib_python_template-1.0.5.dist-info/RECORD
